{
  "siteTitle": "Clara Callejo",
  "siteDescription": "Página de Clara Callejo",
  "author": "Clara Callejo",
  "contactEmail": "claricallejo@gmail.com",
  "contactPhone": " ",
  "socialNetworks": {
    "snapchat": "",
    "youtube": "",
    "facebook": "https://www.instagram.com/comunicacioncc",
    "instagram": "https://www.instagram.com/comunicacioncc",
    "twitter": "",
    "tiktok": "",
    "pinterest": "",
    "tumblr": "",
    "linkedin": "https://www.linkedin.com/in/claricallejo/"
  }
}